RASPA2/__init__.py
RASPA2/output_parser.py
RASPA2/raspa2.py
RASPA2/simulations/lib/libraspa2.cpython-37m-x86_64-linux-gnu.so
RASPA2/share/raspa/framework/AmirjalayerSchmid/framework.def
RASPA2/share/raspa/framework/Demontis/framework.def
RASPA2/share/raspa/framework/CoreShellSastreGale2005/framework.def
RASPA2/share/raspa/framework/Dubbeldam2007FlexibleIRMOF-16/framework.def
RASPA2/share/raspa/framework/DemontisModified/framework.def
RASPA2/share/raspa/framework/CoreShellCatlow/framework.def
RASPA2/share/raspa/framework/CoreShellSchroderSauer/framework.def
RASPA2/share/raspa/framework/NicholasModified/framework.def
RASPA2/share/raspa/framework/Dubbeldam2007FlexibleIRMOF-10/framework.def
RASPA2/share/raspa/framework/Dubbeldam2007FlexibleIRMOF-1/framework.def
RASPA2/share/raspa/framework/Nicholas/framework.def
RASPA2/share/raspa/molecules/Generic/argon.def
RASPA2/share/raspa/molecules/Generic/CO2.def
RASPA2/share/raspa/molecules/Generic/methane.def
RASPA2/share/raspa/molecules/Generic/helium.def
RASPA2/share/raspa/molecules/Generic/N2.def
RASPA2/share/raspa/molecules/TraPPE-EH/methane.def
RASPA2/share/raspa/molecules/TraPPE-UA/CO2.def
RASPA2/share/raspa/molecules/TraPPE-UA/methane.def
RASPA2/share/raspa/molecules/TraPPE-UA/butane.def
RASPA2/share/raspa/molecules/TraPPE-UA/2-methylbutane.def
RASPA2/share/raspa/molecules/TraPPE-UA/pentane.def
RASPA2/share/raspa/molecules/TraPPE-UA/propane.def
RASPA2/share/raspa/molecules/TraPPE-UA/dimethylpropane.def
RASPA2/share/raspa/molecules/TraPPE-UA/ethane.def
RASPA2/share/raspa/molecules/TraPPE-UA/isobutane.def
RASPA2/share/raspa/molecules/TraPPE-UA/heptane.def
RASPA2/share/raspa/molecules/TraPPE-UA/2-methylpentane.def
RASPA2/share/raspa/molecules/EPM2/CO2.def
RASPA2/share/raspa/molecules/TraPPE/2-ethyl-2-hexenal-cis.def
RASPA2/share/raspa/molecules/TraPPE/BDC.def
RASPA2/share/raspa/molecules/TraPPE/C21.def
RASPA2/share/raspa/molecules/TraPPE/C16.def
RASPA2-2.0.4.dist-info/COPYING
RASPA2-2.0.4.dist-info/top_level.txt
RASPA2-2.0.4.dist-info/AUTHORS
RASPA2-2.0.4.dist-info/METADATA
RASPA2-2.0.4.dist-info/LICENSE
RASPA2-2.0.4.dist-info/entry_points.txt
RASPA2-2.0.4.dist-info/RECORD
RASPA2-2.0.4.dist-info/WHEEL
