Metadata-Version: 2.1
Name: RASPA2
Version: 2.0.4
Summary: A general purpose classical simulation package.
Home-page: http://github.com/numat/RASPA2/
Author: David Dubbeldam
Author-email: D.Dubbeldam@uva.nl
License: UNKNOWN
Platform: UNKNOWN
Classifier: Development Status :: 4 - Beta
Classifier: Natural Language :: English
Classifier: Operating System :: Unix
Classifier: Programming Language :: C
Classifier: Programming Language :: Python
Classifier: Programming Language :: Python :: 2
Classifier: Programming Language :: Python :: 3
Classifier: Framework :: IPython
Classifier: Topic :: Scientific/Engineering :: Chemistry
